mopidy_listenbrainz/__init__.py
mopidy_listenbrainz/backend.py
mopidy_listenbrainz/ext.conf
mopidy_listenbrainz/frontend.py
mopidy_listenbrainz/listenbrainz.py
mopidy_listenbrainz/playlists.py
Mopidy_Listenbrainz-0.3.0.dist-info/LICENSE
Mopidy_Listenbrainz-0.3.0.dist-info/METADATA
Mopidy_Listenbrainz-0.3.0.dist-info/WHEEL
Mopidy_Listenbrainz-0.3.0.dist-info/entry_points.txt
Mopidy_Listenbrainz-0.3.0.dist-info/top_level.txt
Mopidy_Listenbrainz-0.3.0.dist-info/RECORD
