Metadata-Version: 2.1
Name: Mopidy-Listenbrainz
Version: 0.3.0
Summary: Mopidy extension for recording played tracks as listens to Listenbrainz
Home-page: https://github.com/suaviloquence/mopidy-listenbrainz
Author: suaviloquence
Author-email: m@mcarr.one
License: Apache License, Version 2.0
Classifier: Environment :: No Input/Output (Daemon)
Classifier: Intended Audience :: End Users/Desktop
Classifier: License :: OSI Approved :: Apache Software License
Classifier: Operating System :: OS Independent
Classifier: Programming Language :: Python :: 3
Classifier: Programming Language :: Python :: 3.7
Classifier: Programming Language :: Python :: 3.8
Classifier: Programming Language :: Python :: 3.9
Classifier: Programming Language :: Python :: 3.10
Classifier: Programming Language :: Python :: 3.11
Classifier: Programming Language :: Python :: 3.12
Classifier: Topic :: Multimedia :: Sound/Audio :: Players
Requires-Python: >=3.7
License-File: LICENSE
Requires-Dist: Mopidy>=3.0.0
Requires-Dist: Pykka>=2.0.1
Requires-Dist: setuptools
Requires-Dist: musicbrainzngs>=0.7.1
Provides-Extra: lint
Requires-Dist: black; extra == "lint"
Requires-Dist: check-manifest; extra == "lint"
Requires-Dist: flake8; extra == "lint"
Requires-Dist: flake8-black; extra == "lint"
Requires-Dist: flake8-bugbear; extra == "lint"
Requires-Dist: flake8-import-order; extra == "lint"
